{"data":{"propertyOrder":{},"properties":{"id":{"name":"id","reference":"scalar","primary":true,"type":"string"},"createdAt":{"name":"createdAt","reference":"scalar","getter":false,"setter":false,"type":"Date"},"updatedAt":{"name":"updatedAt","reference":"scalar","getter":false,"setter":false,"type":"Date"}},"props":[{"name":"id","reference":"scalar","primary":true,"type":"string"},{"name":"createdAt","reference":"scalar","getter":false,"setter":false,"type":"Date"},{"name":"updatedAt","reference":"scalar","getter":false,"setter":false,"type":"Date"}],"primaryKeys":["id"],"filters":{},"hooks":{},"indexes":[],"uniques":[],"className":"BaseEntity","path":"./src/entities/base.entity.ts","abstract":true,"constructorParams":[],"toJsonParams":[],"useCache":true,"compositePK":false,"relations":[]},"origin":"./src/entities/base.entity.ts","hash":"e1811edfcd44c3af552f2be7ed48be0a","version":"4.5.9"}
